udi_draw/__init__.py
udi_draw/__main__.py
udi_draw/buildings.py
udi_draw/simple/__init__.py
udi_draw/simple/shapes.py
udi_draw-0.1.0.dist-info/entry_points.txt
udi_draw-0.1.0.dist-info/WHEEL
udi_draw-0.1.0.dist-info/METADATA
udi_draw-0.1.0.dist-info/RECORD
