Metadata-Version: 2.3
Name: udi_draw
Version: 0.1.0
Summary: An amazing paint app for the command line.
